setup.py
ceshiyong666/__init__.py
ceshiyong666/tianzhidao.py
shijietaidaceshi.egg-info/PKG-INFO
shijietaidaceshi.egg-info/SOURCES.txt
shijietaidaceshi.egg-info/dependency_links.txt
shijietaidaceshi.egg-info/top_level.txt