Metadata-Version: 1.0
Name: shijietaidaceshi
Version: 0.1
Summary: make in chinese
Home-page: https://www.baidu.com/
Author: qitian
Author-email: xzwgm81@163.com
License: UNKNOWN
Platform: UNKNOWN
